[
  {
    "id": "aceites_y_vinagres",
    "name": "Aceites y Vinagres",
    "image": "/img/categorias/AceitesyVinagres.jpg"
  },
  {
    "id": "aceitunas_y_encurtidos",
    "name": "Aceitunas y Encurtidos",
    "image": "/img/categorias/AceitunasYencurtidos.jpg"
  },
  {
    "id": "alimentacion_infantil",
    "name": "Alimentación Infantil",
    "image": "/img/categorias/AlimentacionInfantil.jpg"
  },
  {
    "id": "almibares_mermeladas_y_mieles",
    "name": "Almíbares, Mermeladas y Mieles",
    "image": "/img/categorias/AlmbaresMermeladas&Mieles.png"
  },
  {
    "id": "caldos",
    "name": "Caldos",
    "image": "/img/categorias/caldos.png"
  },
  {
    "id": "carnicos_ibericos",
    "name": "Cárnicos Ibéricos",
    "image": "/img/categorias/carnicosIbericos.png"
  },
  {
    "id": "conservas_de_pescado",
    "name": "Conservas de Pescado",
    "image": "/img/categorias/conservasPescado.jpg"
  },
  {
    "id": "conservas_vegetales",
    "name": "Conservas Vegetales",
    "image": "/img/categorias/ConservasVegetales.jpg"
  },
  {
    "id": "jamones_y_embutidos",
    "name": "Jamones y Embutidos",
    "image": "/img/categorias/Jamones&embutidos.jpg"
  },
  {
    "id": "legumbres_y_arroces",
    "name": "Legumbres y Arroces",
    "image": "/img/categorias/Legumbres&Arroces.jpg"
  },
  {
    "id": "precocinados",
    "name": "Precocinados",
    "image": "/img/categorias/precocinados.jpg"
  },
  {
    "id": "quesos",
    "name": "Quesos",
    "image": "/img/categorias/quesos.png"
  },
  {
    "id": "reposteria",
    "name": "Repostería",
    "image": "/img/categorias/reposteria.png"
  },
  {
    "id": "salsas_ketchup_y_mostaza",
    "name": "Salsas, Ketchup y Mostaza",
    "image": "/img/categorias/salsasKetchup&Mostaza.jpg"
  },
  {
    "id": "siropes",
    "name": "Siropes",
    "image": "/img/categorias/siropes.jpeg"
  },
  {
    "id": "vinos",
    "name": "Vinos",
    "image": "/img/categorias/vinos.png"
  }
]
